{
"skeleton": {
	"hash": "qGaDaRzUa3A",
	"spine": "4.3.75-beta",
	"x": -134.11865,
	"y": -3.2799225,
	"width": 266.9363,
	"height": 349.6077,
	"images": "./images/",
	"audio": null
},
"bones": [
	{ "name": "root" },
	{ "name": "hip", "parent": "root", "x": 0.6469192, "y": 114.41252, "color": "ffcf00ff" },
	{
		"name": "torso",
		"parent": "hip",
		"length": 85.82673,
		"rotation": 93.9296,
		"x": -6.42199,
		"y": 1.975998,
		"color": "ffcf00ff"
	},
	{
		"name": "neck",
		"parent": "torso",
		"length": 18.384506,
		"rotation": -1.5180435,
		"x": 81.67812,
		"y": -6.348399,
		"color": "ffcf00ff"
	},
	{
		"name": "head",
		"parent": "neck",
		"length": 68.28646,
		"rotation": -13.924263,
		"x": 20.93689,
		"y": 11.594276,
		"color": "ffcf00ff"
	},
	{
		"name": "left-shoulder",
		"parent": "torso",
		"length": 35.43316,
		"rotation": -156.96495,
		"x": 74.04638,
		"y": -20.389116,
		"color": "ff0000ff"
	},
	{
		"name": "left-arm",
		"parent": "left-shoulder",
		"length": 35.62285,
		"rotation": 28.166067,
		"x": 37.8584,
		"y": -2.349762,
		"color": "ff0000ff"
	},
	{
		"name": "left-upper-leg",
		"parent": "hip",
		"length": 50.39767,
		"rotation": -89.09777,
		"x": 14.454002,
		"y": 2.813988,
		"color": "ff0000ff"
	},
	{
		"name": "left-lower-leg",
		"parent": "left-upper-leg",
		"length": 49.89856,
		"rotation": -16.657845,
		"x": 56.34396,
		"y": 0.9890461,
		"color": "ff0000ff"
	},
	{
		"name": "left-foot",
		"parent": "left-lower-leg",
		"length": 46.50164,
		"rotation": 102.43323,
		"x": 58.94322,
		"y": -7.61201,
		"color": "ff0000ff"
	},
	{
		"name": "left-hand",
		"parent": "left-arm",
		"length": 11.521948,
		"rotation": 2.704876,
		"x": 35.62277,
		"y": 0.07823181,
		"color": "ff0000ff"
	},
	{ "name": "pelvis", "parent": "hip", "x": 1.4121642, "y": -6.579201, "color": "ffcf00ff" },
	{
		"name": "right-shoulder",
		"parent": "torso",
		"length": 37.24952,
		"rotation": 133.88586,
		"x": 76.02283,
		"y": 18.147917,
		"color": "62ff00ff"
	},
	{
		"name": "right-arm",
		"parent": "right-shoulder",
		"length": 36.74646,
		"rotation": 36.3266,
		"x": 37.60883,
		"y": 0.3119049,
		"color": "62ff00ff"
	},
	{
		"name": "right-upper-leg",
		"parent": "hip",
		"length": 42.45724,
		"rotation": -97.49565,
		"x": -20.078007,
		"y": -6.839988,
		"color": "62ff00ff"
	},
	{
		"name": "right-lower-leg",
		"parent": "right-upper-leg",
		"length": 58.52597,
		"rotation": -14.342007,
		"x": 42.99514,
		"y": -0.6194,
		"color": "62ff00ff"
	},
	{
		"name": "right-foot",
		"parent": "right-lower-leg",
		"length": 45.45873,
		"rotation": 110.30844,
		"x": 64.8894,
		"y": 0.04462051,
		"color": "62ff00ff"
	},
	{
		"name": "right-hand",
		"parent": "right-arm",
		"length": 15.321984,
		"rotation": 2.358873,
		"x": 36.90193,
		"y": 0.3492279,
		"color": "62ff00ff"
	},
	{
		"name": "spear1",
		"parent": "left-hand",
		"length": 65.06642,
		"rotation": 102.43323,
		"x": 0.4830685,
		"y": 17.03218,
		"color": "ffcf00ff"
	},
	{
		"name": "spear2",
		"parent": "spear1",
		"length": 61.41765,
		"rotation": 0.902221,
		"x": 65.05516,
		"y": 0.04217529,
		"color": "ffcf00ff"
	},
	{
		"name": "spear3",
		"parent": "spear2",
		"length": 76.79729,
		"rotation": -0.902221,
		"x": 61.88763,
		"y": 0.5729008,
		"color": "ffcf00ff"
	}
],
"slots": [
	{ "name": "left-shoulder", "bone": "left-shoulder", "attachment": "left-shoulder" },
	{ "name": "left-arm", "bone": "left-arm", "attachment": "left-arm" },
	{ "name": "left-hand-item", "bone": "left-hand", "attachment": "spear" },
	{ "name": "left-hand", "bone": "left-hand", "attachment": "left-hand" },
	{ "name": "left-foot", "bone": "left-foot", "attachment": "left-foot" },
	{ "name": "left-lower-leg", "bone": "left-lower-leg", "attachment": "left-lower-leg" },
	{ "name": "left-upper-leg", "bone": "left-upper-leg", "attachment": "left-upper-leg" },
	{ "name": "neck", "bone": "neck", "attachment": "neck" },
	{ "name": "torso", "bone": "torso", "attachment": "torso" },
	{ "name": "pelvis", "bone": "pelvis", "attachment": "pelvis" },
	{ "name": "right-foot", "bone": "right-foot", "attachment": "right-foot" },
	{ "name": "right-lower-leg", "bone": "right-lower-leg", "attachment": "right-lower-leg" },
	{ "name": "undie-straps", "bone": "pelvis", "attachment": "undie-straps" },
	{ "name": "undies", "bone": "pelvis", "attachment": "undies" },
	{ "name": "right-upper-leg", "bone": "right-upper-leg", "attachment": "right-upper-leg" },
	{ "name": "head", "bone": "head", "attachment": "head" },
	{ "name": "eyes", "bone": "head" },
	{ "name": "right-shoulder", "bone": "right-shoulder", "attachment": "right-shoulder" },
	{ "name": "right-arm", "bone": "right-arm", "attachment": "right-arm" },
	{ "name": "right-hand-thumb", "bone": "right-hand", "attachment": "right-hand-thumb" },
	{ "name": "right-hand-item", "bone": "right-hand", "attachment": "dagger" },
	{ "name": "right-hand", "bone": "right-hand", "attachment": "right-hand" },
	{ "name": "right-hand-item2", "bone": "right-hand", "attachment": "shield" }
],
"skins": [
	{
		"name": "default",
		"attachments": {
			"left-hand-item": {
				"dagger": { "x": 7.882931, "y": -23.45868, "rotation": 10.47712, "width": 26, "height": 108 },
				"spear": {
					"type": "mesh",
					"uvs": [ 1, 0.11236292, 0.7709624, 0.132784, 0.7660807, 0.2178118, 0.7564244, 0.386, 0.747234, 0.5460744, 0.7211727, 1, 0.2883814, 1, 0.2420815, 0.5432775, 0.22589615, 0.3836179, 0.20890936, 0.2160528, 0.20043205, 0.13242875, 0, 0.11519832, 0.45270225, 0, 0.5839923, 0 ],
					"triangles": [ 5, 6, 4, 6, 7, 4, 4, 7, 3, 2, 9, 1, 9, 10, 1, 10, 12, 1, 12, 13, 1, 1, 13, 0, 10, 11, 12, 3, 8, 2, 8, 9, 2, 7, 8, 3 ],
					"vertices": [ 1.0, 20.0, 38.54, -10.89, 1.0, 1.0, 20.0, 30.97, -5.93, 1.0, 2.0, 19.0, 61.48, -5.59, 0.5116, 20.0, -0.31, -6.16, 0.4884, 2.0, 18.0, 64.73, -5.03, 0.50272, 19.0, -0.4, -5.07, 0.49728, 1.0, 10.0, 4.57, 23.91, 1.0, 1.0, 10.0, 41.7, -138.95, 1.0, 1.0, 10.0, 32.43, -141.1, 1.0, 1.0, 10.0, -6.49, 22.41, 1.0, 2.0, 18.0, 65.48, 6.65, 0.50272, 19.0, 0.53, 6.6, 0.49728, 2.0, 19.0, 62.19, 6.67, 0.5116, 20.0, 0.2, 6.1, 0.4884, 1.0, 20.0, 30.97, 6.62, 1.0, 1.0, 20.0, 37.26, 11.09, 1.0, 1.0, 20.0, 79.75, 1.6, 1.0, 1.0, 20.0, 79.78, -1.29, 1.0 ],
					"hull": 14,
					"edges": [ 24, 22, 22, 20, 10, 12, 2, 0, 24, 26, 0, 26, 8, 10, 12, 14, 6, 8, 14, 16, 2, 4, 4, 6, 16, 18, 18, 20, 20, 2 ],
					"width": 22.0,
					"height": 368.0
				}
			},
			"right-hand-item": {
				"dagger": {
					"type": "mesh",
					"uvs": [ 0.7809175, 0.3845325, 1, 0.3840599, 1, 0.4488154, 0.7395351, 0.4687043, 0.7464197, 0.813445, 0.3402276, 1, 0.15434295, 1, 0.11303533, 0.7885837, 0.23007374, 0.4736764, 0, 0.4504729, 0, 0.3862174, 0.22367942, 0.3857348, 0.24384338, 0, 1, 0 ],
					"triangles": [ 0, 12, 13, 11, 12, 0, 0, 1, 2, 9, 10, 11, 3, 11, 0, 3, 0, 2, 8, 11, 3, 9, 11, 8, 5, 6, 7, 4, 5, 8, 4, 8, 3, 5, 7, 8 ],
					"vertices": [ 15.49, -12.83, 21.14, -13.57, 20.16, -20.5, 13.16, -21.68, 8.13, -58.57, -5.14, -77.04, -9.92, -76.37, -7.8, -53.61, -0.03, -20.36, -5.61, -17.04, -4.64, -10.17, 1.13, -10.93, 7.47, 30.24, 26.93, 27.5 ],
					"hull": 14,
					"edges": [ 22, 20, 24, 26, 22, 24, 2, 0, 0, 22, 0, 26, 12, 14, 14, 16, 18, 20, 16, 18, 2, 4, 4, 6, 6, 8, 10, 12, 8, 10 ],
					"width": 26.0,
					"height": 108.0
				}
			},
			"right-hand-item2": {
				"shield": { "rotation": 93.49905, "width": 70, "height": 72 }
			}
		}
	},
	{
		"name": "goblin",
		"attachments": {
			"eyes": {
				"eyes-closed": { "name": "goblin/eyes-closed", "x": 29.192566, "y": -24.899075, "rotation": -88.92847, "width": 34, "height": 12 }
			},
			"head": {
				"head": {
					"name": "goblin/head",
					"type": "mesh",
					"uvs": [ 3.70359E-8, 0.6049488, 0.1417244, 0.5145095, 0.242182, 0.552292, 0.3266756, 0.6780698, 0.379695, 0.7935243, 0.535054, 0.9301452, 0.8605681, 1, 0.9407137, 0.9416906, 0.9209856, 0.6992363, 0.988801, 0.6549789, 0.990034, 0.5164337, 0.8963254, 0.4356155, 0.9448712, 0.4191675, 1, 0.3971308, 1, 0.2836006, 0.9401727, 0.2702738, 0.8790633, 0.2566614, 0.8075489, 0.16044915, 0.6669858, 0.019979537, 0.4734036, 0.01805556, 0.2921514, 0.19893414, 0.2539281, 0.3182371, 0.09117104, 0.3240095, 0, 0.4433125, 0.4327149, 0.6915393, 0.4660055, 0.4779489, 0.3599668, 0.3124645, 0.7347384, 0.6859392, 0.722156, 0.5742576, 0.8817962, 0.5583031, 0.802679, 0.5101598 ],
					"triangles": [ 5, 27, 6, 7, 27, 8, 7, 6, 27, 4, 24, 5, 5, 24, 27, 4, 3, 24, 27, 29, 8, 8, 29, 9, 24, 28, 27, 24, 25, 28, 24, 3, 25, 29, 28, 30, 29, 27, 28, 25, 2, 26, 25, 3, 2, 9, 29, 10, 0, 23, 1, 28, 25, 30, 29, 11, 10, 29, 30, 11, 2, 21, 26, 2, 1, 21, 23, 22, 1, 1, 22, 21, 30, 16, 11, 30, 17, 16, 30, 25, 17, 17, 26, 18, 18, 26, 19, 26, 17, 25, 11, 15, 12, 11, 16, 15, 12, 15, 13, 15, 14, 13, 21, 20, 26, 26, 20, 19 ],
					"vertices": [ 14.56, 50.42, 23.12, 35.48, 17.47, 26.36, 11.58, 16.87, 3.75, 11.71, -5.9, -3.92, -11.83, -37.24, -8.32, -45.64, 7.75, -44.24, 10.4, -51.34, 19.53, -51.83, 25.21, -43.16, 26.13, -47.43, 27.36, -53.16, 34.84, -53.46, 35.97, -47.34, 37.11, -41.09, 43.75, -33.98, 53.59, -19.88, 54.51, 0.04, 43.32, 19.17, 35.61, 23.41, 35.89, 40.18, 28.4, 49.87, 10.26, 5.99, 24.21, 2.0, 35.55, 12.48, 9.39, -25.11, 16.8, -24.31, 17.21, -40.66, 20.69, -33.02 ],
					"hull": 24,
					"edges": [ 0, 2, 6, 8, 8, 10, 10, 12, 12, 14, 14, 16, 16, 18, 18, 20, 20, 22, 26, 28, 32, 34, 34, 36, 36, 38, 38, 40, 40, 42, 42, 44, 44, 46, 0, 46, 6, 48, 48, 50, 50, 52, 52, 42, 2, 4, 4, 6, 4, 52, 2, 44, 22, 32, 22, 24, 24, 26, 28, 30, 30, 32, 24, 30, 16, 54, 54, 56, 20, 58, 58, 54, 16, 58, 22, 60, 60, 56, 58, 60 ],
					"width": 103.0,
					"height": 66.0
				}
			},
			"left-arm": {
				"left-arm": {
					"name": "goblin/left-arm",
					"type": "mesh",
					"uvs": [ 0.689927, 0.2928419, 1, 0.4636409, 1, 0.74644, 0.8408993, 1, 0.6634406, 1, 0.3376581, 0.6428402, 0, 0.441241, 0, 0, 0.3429556, 0 ],
					"triangles": [ 3, 4, 2, 4, 5, 2, 5, 0, 2, 0, 1, 2, 0, 5, 8, 5, 6, 8, 6, 7, 8 ],
					"vertices": [ 18.6, 8.81, 32.2, 10.32, 38.02, 1.63, 38.08, -9.63, 32.32, -13.5, 14.37, -9.62, -0.76, -10.78, -9.85, 2.78, 1.29, 10.25 ],
					"hull": 9,
					"edges": [ 14, 16, 16, 0, 0, 2, 2, 4, 6, 4, 6, 8, 8, 10, 12, 14, 10, 12 ],
					"width": 37.0,
					"height": 35.0
				}
			},
			"left-foot": {
				"left-foot": {
					"name": "goblin/left-foot",
					"type": "mesh",
					"uvs": [ 0.15733713, 0.3187368, 0.08195284, 0.7850251, 0.15884484, 0.9936694, 0.4163335, 0.9680454, 0.6882251, 0.976368, 1, 0.9638842, 0.9938552, 0.7350135, 0.852948, 0.518627, 0.6147946, 0.31056315, 0.46991795, 0, 0.4803264, 0.756043, 0.759947, 0.7770632 ],
					"triangles": [ 0, 9, 8, 10, 0, 8, 10, 8, 7, 11, 10, 7, 11, 7, 6, 1, 0, 10, 11, 6, 5, 3, 1, 10, 4, 10, 11, 4, 11, 5, 3, 10, 4, 2, 1, 3 ],
					"vertices": [ 2.28, 13.07, -1.77, -1.64, 3.6, -7.81, 20.26, -6.04, 37.92, -5.28, 58.13, -3.71, 57.32, 3.35, 47.78, 9.51, 31.95, 15.05, 21.99, 24.12, 24.03, 0.76, 42.21, 1.16 ],
					"hull": 10,
					"edges": [ 0, 2, 2, 4, 4, 6, 6, 8, 8, 10, 10, 12, 12, 14, 14, 16, 16, 18, 0, 18, 6, 20, 20, 16, 2, 20, 8, 22, 22, 14, 20, 22, 22, 10 ],
					"width": 65.0,
					"height": 31.0
				}
			},
			"left-hand": {
				"left-hand": {
					"name": "goblin/left-hand",
					"type": "mesh",
					"uvs": [ 0.5180096, 0.12578267, 1, 0.16285557, 0.9978891, 0.5057812, 0.6974534, 1, 0.3744545, 1, 0, 0.800512, 0, 0.4279279, 0.17601077, 0, 0.4356766, 0 ],
					"triangles": [ 2, 0, 1, 0, 5, 6, 6, 7, 0, 0, 7, 8, 3, 4, 0, 4, 5, 0, 2, 3, 0 ],
					"vertices": [ -3.11, 15.43, 10.84, 22.27, 15.5, 14.56, 18.36, -8.96, 9.48, -14.33, -4.59, -14.3, -11.64, -2.64, -14.89, 13.68, -7.76, 18.0 ],
					"hull": 9,
					"edges": [ 16, 0, 0, 2, 2, 4, 4, 6, 6, 8, 8, 10, 10, 12, 14, 16, 12, 14 ],
					"width": 36.0,
					"height": 41.0
				}
			},
			"left-lower-leg": {
				"left-lower-leg": {
					"name": "goblin/left-lower-leg",
					"type": "mesh",
					"uvs": [ 0.955088, 0.2074963, 0.8192703, 0.6521376, 0.9475428, 0.77308, 0.6784225, 0.973465, 0.4646353, 1, 0.2684542, 1, 0.04963683, 0.9070653, 0.2106059, 0.6011522, 0.07478805, 0.4019528, 0.1854545, 0, 0.2885753, 0 ],
					"triangles": [ 10, 8, 9, 1, 7, 10, 7, 8, 10, 0, 1, 10, 1, 4, 7, 3, 1, 2, 5, 6, 7, 7, 4, 5, 1, 3, 4 ],
					"vertices": [ -0.2, 6.82, 30.97, 10.96, 37.97, 17.34, 53.88, 12.6, 57.59, 6.32, 59.35, 0.09, 55.05, -8.63, 33.0, -9.34, 20.8, -17.44, -7.28, -21.57, -8.2, -18.29 ],
					"hull": 11,
					"edges": [ 20, 0, 0, 2, 2, 4, 4, 6, 6, 8, 8, 10, 10, 12, 12, 14, 14, 16, 18, 20, 16, 18 ],
					"width": 33.0,
					"height": 70.0
				}
			},
			"left-shoulder": {
				"left-shoulder": {
					"name": "goblin/left-shoulder",
					"type": "mesh",
					"uvs": [ 0.7377047, 0.4069248, 1, 0.7523793, 1, 1, 0.6204634, 1, 0.261843, 0.5660158, 0, 0.2978342, 0, 0, 0.4411532, 0 ],
					"triangles": [ 3, 1, 2, 3, 0, 1, 3, 4, 0, 4, 7, 0, 4, 5, 7, 5, 6, 7 ],
					"vertices": [ 15.18, 5.74, 32.17, 5.33, 41.79, 0.22, 36.63, -9.5, 14.89, -9.73, 0.9, -10.9, -10.67, -4.75, -4.67, 6.55 ],
					"hull": 8,
					"edges": [ 12, 14, 14, 0, 4, 2, 0, 2, 4, 6, 6, 8, 10, 12, 8, 10 ],
					"width": 29.0,
					"height": 44.0
				}
			},
			"left-upper-leg": {
				"left-upper-leg": {
					"name": "goblin/left-upper-leg",
					"type": "mesh",
					"uvs": [ 1, 0.12167889, 1, 0.5487324, 0.910675, 0.789074, 0.7656756, 1, 0.3087075, 0.957909, 0, 0.687773, 0, 0.2190073, 0.5196159, 0, 0.8755237, 0 ],
					"triangles": [ 7, 8, 0, 5, 6, 7, 0, 1, 7, 4, 5, 7, 1, 4, 7, 2, 4, 1, 3, 4, 2 ],
					"vertices": [ 2.34, 13.07, 33.51, 12.57, 51.0, 9.34, 66.32, 4.31, 63.01, -10.71, 43.13, -20.59, 8.91, -20.04, -6.8, -2.64, -6.61, 9.1 ],
					"hull": 9,
					"edges": [ 10, 8, 8, 6, 6, 4, 4, 2, 10, 12, 12, 14, 14, 16, 2, 0, 16, 0 ],
					"width": 33.0,
					"height": 73.0
				}
			},
			"neck": {
				"neck": {
					"name": "goblin/neck",
					"type": "mesh",
					"uvs": [ 0.819678, 0.2736537, 0.921011, 0.820481, 0.471346, 1, 0.1567915, 0.9354073, 0, 0.7556033, 0.1926803, 0.5183358, 0.15468043, 0.357068, 0, 0.21989775, 0.1356805, 0, 0.6887897, 0, 0.7014564, 0.538726 ],
					"triangles": [ 3, 5, 2, 2, 10, 1, 2, 5, 10, 3, 4, 5, 10, 0, 1, 0, 10, 6, 10, 5, 6, 7, 8, 6, 6, 9, 0, 6, 8, 9 ],
					"vertices": [ 18.63, -11.66, -3.98, -13.86, -10.29, 2.77, -6.92, 13.9, 0.8, 19.06, 10.06, 11.51, 16.75, 12.45, 22.72, 17.65, 31.4, 12.2, 30.12, -7.68, 8.05, -6.71 ],
					"hull": 10,
					"edges": [ 14, 12, 12, 10, 10, 8, 8, 6, 6, 4, 4, 2, 2, 20, 20, 0, 0, 18, 16, 18, 14, 16, 0, 2 ],
					"width": 36.0,
					"height": 41.0
				}
			},
			"pelvis": {
				"pelvis": {
					"name": "goblin/pelvis",
					"type": "mesh",
					"uvs": [ 1, 1, 0, 1, 0, 0, 1, 0 ],
					"triangles": [ 1, 2, 3, 1, 3, 0 ],
					"vertices": [ 25.38, -20.73, -36.62, -20.73, -36.62, 22.27, 25.38, 22.27 ],
					"hull": 4,
					"edges": [ 0, 2, 2, 4, 4, 6, 0, 6 ],
					"width": 62.0,
					"height": 43.0
				}
			},
			"right-arm": {
				"right-arm": {
					"name": "goblin/right-arm",
					"type": "mesh",
					"uvs": [ 1, 0.09223175, 1, 0.850105, 0.7205844, 1, 0.2438467, 1, 0, 0.865585, 0.2082271, 0.10919984, 0.5090332, 0, 0.8534232, 0 ],
					"triangles": [ 1, 2, 6, 6, 2, 5, 1, 6, 0, 4, 5, 3, 2, 3, 5, 6, 7, 0 ],
					"vertices": [ -4.75, 8.89, 33.03, 11.74, 40.99, 5.9, 41.82, -5.03, 35.54, -11.13, -2.54, -9.2, -8.5, -2.72, -9.1, 5.18 ],
					"hull": 8,
					"edges": [ 8, 6, 4, 6, 4, 2, 12, 14, 2, 0, 14, 0, 10, 12, 8, 10 ],
					"width": 23.0,
					"height": 50.0
				}
			},
			"right-foot": {
				"right-foot": {
					"name": "goblin/right-foot",
					"type": "mesh",
					"uvs": [ 0.4085105, 0.004707575, 0.5908776, 0.3340438, 0.7595923, 0.483111, 0.8890726, 0.5975127, 0.975327, 0.8939153, 0.9038588, 1, 0.6722035, 1, 0.3863308, 1, 0.08074273, 1, 0, 0.8892103, 0, 0.6598452, 0, 0.4657782, 0.0906004, 0.09880364, 0.3050049, 0, 0.4746113, 0.7125795, 0.715009, 0.746814 ],
					"triangles": [ 1, 10, 11, 1, 13, 0, 14, 1, 2, 1, 12, 13, 12, 1, 11, 14, 10, 1, 15, 14, 2, 15, 2, 3, 9, 10, 14, 15, 3, 4, 7, 8, 9, 14, 7, 9, 6, 14, 15, 5, 6, 15, 7, 14, 6, 4, 5, 15 ],
					"vertices": [ 17.36, 26.0, 29.14, 15.44, 39.89, 10.81, 48.15, 7.25, 53.84, -2.38, 49.43, -6.0, 34.85, -6.39, 16.84, -6.87, -2.4, -7.38, -7.59, -3.87, -7.79, 3.7, -7.96, 10.1, -2.57, 22.36, 10.84, 25.98, 22.15, 2.76, 37.32, 2.03 ],
					"hull": 14,
					"edges": [ 0, 2, 6, 8, 8, 10, 16, 18, 22, 24, 24, 26, 0, 26, 10, 12, 2, 4, 4, 6, 12, 14, 14, 16, 18, 20, 20, 22, 2, 28, 28, 14, 20, 28, 4, 30, 30, 12, 28, 30, 30, 8 ],
					"width": 63.0,
					"height": 33.0
				}
			},
			"right-hand": {
				"right-hand": {
					"name": "goblin/right-hand",
					"type": "mesh",
					"uvs": [ 0.17957264, 0, 0, 0.4477236, 0, 0.7973437, 0.20057233, 0.9426403, 0.5505708, 1, 0.8539028, 1, 0.898236, 0.8200463, 0.8259028, 0.7428574, 0.8422363, 0.4999396, 0.9635691, 0.3410214, 0.660237, 0 ],
					"triangles": [ 8, 10, 9, 0, 10, 1, 8, 2, 1, 8, 1, 10, 7, 3, 8, 3, 2, 8, 4, 3, 7, 5, 7, 6, 4, 7, 5 ],
					"vertices": [ -10.83, -9.45, 5.95, -15.35, 18.88, -14.9, 24.01, -7.5, 25.69, 5.16, 25.32, 16.08, 18.61, 17.44, 15.85, 14.74, 6.84, 15.02, 0.82, 19.19, -11.42, 7.84 ],
					"hull": 11,
					"edges": [ 0, 2, 2, 4, 4, 6, 6, 8, 8, 10, 10, 12, 12, 14, 14, 16, 16, 18, 18, 20, 0, 20 ],
					"width": 36.0,
					"height": 37.0
				}
			},
			"right-hand-thumb": {
				"right-hand-thumb": {
					"name": "goblin/right-hand",
					"type": "mesh",
					"uvs": [ 0.88538, 0.222626, 0.7616778, 0.3594049, 0.7508874, 0.7830815, 0.95326, 0.849811, 1, 0.6030292 ],
					"triangles": [ 1, 0, 4, 2, 1, 4, 3, 2, 4 ],
					"vertices": [ -2.82, 15.98, 2.4, 11.72, 18.08, 11.91, 20.28, 19.28, 11.09, 20.62 ],
					"hull": 5,
					"edges": [ 2, 4, 4, 6, 6, 8, 2, 0, 0, 8 ],
					"width": 36.0,
					"height": 37.0
				}
			},
			"right-lower-leg": {
				"right-lower-leg": {
					"name": "goblin/right-lower-leg",
					"type": "mesh",
					"uvs": [ 1, 0.2726124, 0.8131241, 0.5259288, 0.7958732, 0.7179591, 0.9554444, 0.8098885, 0.8519389, 0.9549325, 0.4724182, 1, 0.14033763, 1, 0, 0.8773032, 0.14896297, 0.6791445, 0.16190127, 0.3032556, 0.6061128, 0 ],
					"triangles": [ 1, 10, 0, 9, 10, 1, 8, 9, 1, 2, 8, 1, 4, 2, 3, 6, 7, 8, 5, 6, 8, 2, 5, 8, 4, 5, 2 ],
					"vertices": [ 6.27, 8.46, 23.32, 8.05, 37.1, 12.9, 41.45, 20.83, 53.07, 21.47, 61.33, 10.06, 65.78, -1.04, 59.0, -9.19, 43.02, -9.82, 16.33, -20.01, -12.8, -9.26 ],
					"hull": 11,
					"edges": [ 0, 2, 2, 4, 4, 6, 6, 8, 8, 10, 10, 12, 12, 14, 14, 16, 16, 18, 0, 20, 18, 20 ],
					"width": 36.0,
					"height": 76.0
				}
			},
			"right-shoulder": {
				"right-shoulder": {
					"name": "goblin/right-shoulder",
					"type": "mesh",
					"uvs": [ 0.6200804, 0.03708865, 0.9213104, 0.0904887, 1, 0.383199, 0.7204904, 0.6937093, 0.3165686, 1, 0, 1, 0, 0.7510647, 0.2823379, 0.4998874 ],
					"triangles": [ 4, 6, 7, 4, 7, 3, 4, 5, 6, 7, 0, 3, 2, 0, 1, 2, 3, 0 ],
					"vertices": [ -3.17, -11.05, -9.0, -0.58, -1.01, 10.34, 16.69, 11.17, 37.41, 8.2, 45.46, -1.16, 36.96, -8.46, 21.21, -7.48 ],
					"hull": 8,
					"edges": [ 10, 12, 12, 14, 14, 0, 0, 2, 2, 4, 4, 6, 8, 10, 6, 8 ],
					"width": 39.0,
					"height": 45.0
				}
			},
			"right-upper-leg": {
				"right-upper-leg": {
					"name": "goblin/right-upper-leg",
					"type": "mesh",
					"uvs": [ 0.2701891, 0, 0.11618906, 0.1817702, 0, 0.7068813, 0, 0.89577, 0.266689, 1, 0.487189, 1, 0.676189, 0.8353256, 1, 0.5161036, 1, 0.255437, 0.7461889, 0.05710345 ],
					"triangles": [ 9, 8, 7, 9, 1, 0, 6, 9, 7, 6, 1, 9, 2, 1, 6, 4, 3, 2, 6, 4, 2, 5, 4, 6 ],
					"vertices": [ -9.86, -10.37, 2.18, -14.07, 35.49, -13.67, 47.29, -12.11, 52.62, -2.27, 51.64, 5.17, 40.51, 10.18, 19.14, 18.47, 2.85, 16.33, -8.41, 6.14 ],
					"hull": 10,
					"edges": [ 0, 2, 2, 4, 4, 6, 6, 8, 8, 10, 10, 12, 12, 14, 14, 16, 16, 18, 0, 18 ],
					"width": 34.0,
					"height": 63.0
				}
			},
			"torso": {
				"torso": {
					"name": "goblin/torso",
					"type": "mesh",
					"uvs": [ 0, 0.3328751, 0.15945788, 0.4648876, 0.1576165, 0.6031443, 0.15502043, 0.7980618, 0.3280788, 0.9347889, 0.6875076, 1, 0.8073172, 1, 1, 0.7776313, 1, 0.661479, 1, 0.56704, 0.9320769, 0.47710305, 0.8694406, 0.3941665, 0.838379, 0.2260077, 0.6808515, 0, 0.14836423, 0, 0, 0.07199317, 0.787349, 0.8624962, 0.4367949, 0.7964902, 0.7673807, 0.6173304, 0.44345105, 0.5874705, 0.5432924, 0.3831657, 0.7769215, 0.7344698, 0.664788, 0.5101245 ],
					"triangles": [ 5, 16, 6, 6, 16, 7, 4, 17, 5, 5, 17, 16, 4, 3, 17, 17, 21, 16, 16, 21, 7, 3, 2, 17, 21, 19, 18, 21, 17, 19, 17, 2, 19, 21, 8, 7, 21, 18, 8, 18, 9, 8, 19, 22, 18, 18, 10, 9, 18, 22, 10, 2, 1, 19, 19, 20, 22, 19, 1, 20, 22, 11, 10, 22, 20, 11, 20, 1, 14, 20, 12, 11, 1, 0, 14, 20, 13, 12, 20, 14, 13, 0, 15, 14 ],
					"vertices": [ 56.93, 27.95, 43.37, 18.24, 30.16, 19.5, 11.53, 21.29, -2.55, 10.69, -10.89, -13.12, -11.59, -21.24, 8.55, -36.13, 19.66, -37.09, 28.69, -37.86, 37.69, -34.01, 45.99, -30.45, 56.4, -29.07, 84.79, -20.92, 87.9, 15.15, 81.89, 25.8, 1.67, -21.02, 10.04, 2.19, 25.23, -18.25, 29.99, 0.01, 48.54, -8.4, 13.98, -21.37, 35.91, -15.6 ],
					"hull": 16,
					"edges": [ 0, 2, 6, 8, 8, 10, 10, 12, 12, 14, 22, 24, 24, 26, 26, 28, 28, 30, 0, 30, 14, 32, 32, 34, 34, 6, 18, 36, 36, 38, 2, 4, 4, 6, 38, 4, 2, 40, 40, 22, 40, 38, 38, 34, 32, 10, 34, 8, 40, 28, 14, 16, 16, 18, 32, 42, 42, 36, 16, 42, 42, 34, 18, 20, 20, 22, 36, 44, 44, 40, 20, 44 ],
					"width": 68.0,
					"height": 96.0
				}
			},
			"undie-straps": {
				"undie-straps": {
					"name": "goblin/undie-straps",
					"type": "mesh",
					"uvs": [ 0.3609779, 0.4495974, 0.662977, 0.6059125, 1, 0.19486117, 1, 0.5711758, 0.7589767, 1, 0.38697785, 1, 0, 0.2643349, 0, 0, 0.12497856, 0 ],
					"triangles": [ 6, 7, 8, 6, 8, 0, 3, 1, 2, 5, 0, 1, 6, 0, 5, 4, 1, 3, 5, 1, 4 ],
					"vertices": [ -10.56, 12.88, 6.54, 9.91, 25.62, 17.72, 25.62, 10.57, 11.97, 2.42, -9.09, 2.42, -31.0, 16.4, -31.0, 21.42, -23.93, 21.42 ],
					"hull": 9,
					"edges": [ 14, 16, 16, 0, 0, 2, 2, 4, 4, 6, 6, 8, 8, 10, 12, 14, 10, 12, 0, 10, 2, 8 ],
					"width": 55.0,
					"height": 19.0
				}
			},
			"undies": {
				"undies": {
					"name": "goblin/undies",
					"type": "mesh",
					"uvs": [ 0, 0.3202957, 0.1489335, 0.5945705, 0.2243776, 1, 0.3590995, 1, 0.5099878, 1, 0.795598, 0.584536, 0.9842082, 0.2801579, 1, 0.005883038, 0.4695713, 0.17646867, 0, 0.03933108, 0.4884322, 0.5912257, 0.4811459, 0.4309963 ],
					"triangles": [ 6, 8, 7, 0, 9, 8, 11, 8, 6, 0, 8, 11, 5, 11, 6, 10, 11, 5, 1, 0, 11, 1, 11, 10, 3, 2, 1, 10, 3, 1, 4, 10, 5, 3, 10, 4 ],
					"vertices": [ -13.22, 5.57, -8.0, -2.48, -5.49, -14.28, -0.64, -14.36, 4.79, -14.46, 15.28, -2.59, 22.22, 6.12, 22.93, 14.06, 3.75, 9.45, -13.08, 13.72, 4.22, -2.59, 4.04, 2.06 ],
					"hull": 10,
					"edges": [ 0, 2, 2, 4, 8, 10, 10, 12, 12, 14, 14, 16, 16, 18, 0, 18, 4, 6, 6, 8, 6, 20, 16, 22, 22, 20, 0, 22, 22, 12, 2, 20, 20, 10 ],
					"width": 36.0,
					"height": 29.0
				}
			}
		}
	},
	{
		"name": "goblingirl",
		"attachments": {
			"eyes": {
				"eyes-closed": { "name": "goblingirl/eyes-closed", "x": 28.00168, "y": -25.5487, "rotation": -87.0496, "width": 37, "height": 21 }
			},
			"head": {
				"head": { "name": "goblingirl/head", "x": 27.71762, "y": -4.323658, "rotation": -85.58442, "width": 103, "height": 81 }
			},
			"left-arm": {
				"left-arm": { "name": "goblingirl/left-arm", "x": 19.64079, "y": -2.427963, "rotation": 33.05112, "width": 37, "height": 35 }
			},
			"left-foot": {
				"left-foot": { "name": "goblingirl/left-foot", "type": "linkedmesh", "skin": "goblin", "source": "left-foot", "width": 65.0, "height": 31.0 }
			},
			"left-hand": {
				"left-hand": {
					"name": "goblingirl/left-hand",
					"x": 4.341694,
					"y": 2.3908234,
					"scaleX": 0.8964562,
					"scaleY": 0.8964562,
					"rotation": 30.34625,
					"width": 35,
					"height": 40
				}
			},
			"left-lower-leg": {
				"left-lower-leg": { "name": "goblingirl/left-lower-leg", "x": 25.02169, "y": -0.6063051, "rotation": 105.75562, "width": 33, "height": 70 }
			},
			"left-shoulder": {
				"left-shoulder": { "name": "goblingirl/left-shoulder", "x": 19.808914, "y": -0.4276123, "rotation": 61.21719, "width": 28, "height": 46 }
			},
			"left-upper-leg": {
				"left-upper-leg": { "name": "goblingirl/left-upper-leg", "x": 30.21813, "y": -2.951473, "rotation": 89.09777, "width": 33, "height": 70 }
			},
			"neck": {
				"neck": { "name": "goblingirl/neck", "x": 6.164093, "y": -3.1470556, "rotation": -98.86092, "width": 35, "height": 41 }
			},
			"pelvis": {
				"pelvis": { "name": "goblingirl/pelvis", "x": -3.879083, "y": 3.186577, "width": 62, "height": 43 }
			},
			"right-arm": {
				"right-arm": { "name": "goblingirl/right-arm", "x": 16.851105, "y": -0.6603317, "rotation": 93.52624, "width": 28, "height": 50 }
			},
			"right-foot": {
				"right-foot": { "name": "goblingirl/right-foot", "type": "linkedmesh", "skin": "goblin", "source": "right-foot", "width": 63.0, "height": 33.0 }
			},
			"right-hand": {
				"right-hand": { "name": "goblingirl/right-hand", "x": 7.217323, "y": 3.437336, "rotation": 91.16736, "width": 36, "height": 37 }
			},
			"right-hand-thumb": {
				"right-hand-thumb": { "name": "goblingirl/right-hand", "x": 7.217323, "y": 3.437336, "rotation": 91.16736, "width": 36, "height": 37 }
			},
			"right-lower-leg": {
				"right-lower-leg": { "name": "goblingirl/right-lower-leg", "x": 26.15058, "y": -3.2782974, "rotation": 111.83766, "width": 36, "height": 76 }
			},
			"right-shoulder": {
				"right-shoulder": { "name": "goblingirl/right-shoulder", "x": 14.460388, "y": 0.4584351, "rotation": 129.85283, "width": 39, "height": 45 }
			},
			"right-upper-leg": {
				"right-upper-leg": { "name": "goblingirl/right-upper-leg", "x": 19.695267, "y": 2.130188, "rotation": 97.49565, "width": 34, "height": 63 }
			},
			"torso": {
				"torso": { "name": "goblingirl/torso", "x": 36.28168, "y": -5.142856, "rotation": -95.74776, "width": 68, "height": 96 }
			},
			"undie-straps": {
				"undie-straps": { "name": "goblingirl/undie-straps", "x": -1.51909, "y": 14.186577, "width": 55, "height": 19 }
			},
			"undies": {
				"undies": { "name": "goblingirl/undies", "x": 5.400915, "y": 1.7065887, "width": 36, "height": 29 }
			}
		}
	}
],
"animations": {
	"walk": {
		"slots": {
			"eyes": {
				"attachment": [
					{ "time": 0.7, "name": "eyes-closed" },
					{ "time": 0.8 }
				]
			}
		},
		"bones": {
			"head": {
				"rotate": [
					{
						"value": 3.602418,
						"curve": [ 0, 3.602418, 0.09386973, -0.8890743 ]
					},
					{ "time": 0.13333334, "value": -0.2083187 },
					{ "time": 0.23333333, "value": 6.109963 },
					{ "time": 0.3666667, "value": 3.456826 },
					{
						"time": 0.5,
						"value": 5.17656,
						"curve": [ 0.5, 5.17656, 0.6173371, -1.4047875 ]
					},
					{ "time": 0.6666667, "value": 1.1077137 },
					{ "time": 0.7333333, "value": 6.094682 },
					{ "time": 0.8666667, "value": 2.285569 },
					{ "time": 1, "value": 3.602418 }
				]
			},
			"hip": {
				"translate": [
					{ "y": -8.403984 },
					{
						"time": 0.13333334,
						"y": -9.352982,
						"curve": [ 0.1660205, 0, 0.2008039, 0, 0.1660205, -8.908665, 0.2008039, -1.1377945 ]
					},
					{
						"time": 0.23333333,
						"y": -0.5935135,
						"curve": [ 0.2767374, 0, 0.3191642, 0, 0.2767374, -1.915442, 0.3191642, -2.963724 ]
					},
					{ "time": 0.3666667, "y": -3.965286 },
					{ "time": 0.5, "y": -8.403984 },
					{
						"time": 0.6333333,
						"y": -10.006058,
						"curve": [ 0.669253, 0, 0.6979885, 0, 0.669253, -7.786912, 0.6979885, -6.494446 ]
					},
					{
						"time": 0.7333333,
						"y": -5.299522,
						"curve": [ 0.7555474, 0, 0.7775115, 0, 0.7555474, -4.274181, 0.7775115, -3.354965 ]
					},
					{
						"time": 0.8,
						"y": -2.4978714,
						"curve": [ 0.821475, 0, 0.8434506, 0, 0.821475, -3.015679, 0.8434506, -3.495956 ]
					},
					{ "time": 0.8666667, "y": -3.965286 },
					{ "time": 1, "y": -8.403984 }
				]
			},
			"left-arm": {
				"rotate": [
					{
						"value": 28.377306,
						"curve": [ 0.16954023, 28.377306, 0.341954, 60.09067 ]
					},
					{
						"time": 0.5,
						"value": 60.09067,
						"curve": [ 0.6408046, 60.09067, 0.8433907, 28.54162 ]
					},
					{ "time": 1, "value": 28.377306 }
				]
			},
			"left-foot": {
				"rotate": [
					{ "value": -14.566597 },
					{ "time": 0.13333334, "value": -10.420296 },
					{ "time": 0.23333333, "value": -5.014335 },
					{ "time": 0.3, "value": 6.671051 },
					{ "time": 0.3666667, "value": 3.8732834 },
					{ "time": 0.5, "value": -3.8769 },
					{ "time": 0.6333333, "value": 2.781441 },
					{ "time": 0.7333333, "value": -11.995087 },
					{ "time": 0.8666667, "value": -12.451485 },
					{ "time": 1, "value": -14.566597 }
				]
			},
			"left-hand": {
				"rotate": [
					{
						"value": -21.23881,
						"curve": [ 0.1479885, -21.23881, 0.3778736, -27.208485 ]
					},
					{
						"time": 0.5,
						"value": -27.282276,
						"curve": [ 0.6206896, -27.282276, 0.875, -21.39538 ]
					},
					{ "time": 1, "value": -21.23881 }
				]
			},
			"left-lower-leg": {
				"rotate": [
					{ "value": -18.0531 },
					{ "time": 0.13333334, "value": -63.50577 },
					{ "time": 0.23333333, "value": -83.01877 },
					{ "time": 0.5, "value": 5.116844 },
					{ "time": 0.6333333, "value": -28.29769 },
					{ "time": 0.7333333, "value": -27.521744 },
					{ "time": 0.8666667, "value": 3.5338974 },
					{ "time": 1, "value": -18.0531 }
				],
				"translate": [
					{},
					{ "time": 0.23333333, "x": 2.556618, "y": -0.4729633 },
					{ "time": 0.5 }
				]
			},
			"left-shoulder": {
				"rotate": [
					{
						"value": 6.255386,
						"curve": [ 0.16954023, 6.255386, 0.341954, -11.788895 ]
					},
					{
						"time": 0.5,
						"value": -11.788895,
						"curve": [ 0.6408046, -11.788895, 0.8433907, 6.161894 ]
					},
					{ "time": 1, "value": 6.255386 }
				],
				"translate": [
					{ "x": 1.1536636, "y": 0.23729134 }
				]
			},
			"left-upper-leg": {
				"rotate": [
					{ "value": -26.55841 },
					{ "time": 0.13333334, "value": -8.785103 },
					{ "time": 0.23333333, "value": 9.513512 },
					{ "time": 0.3666667, "value": 30.74426 },
					{ "time": 0.5, "value": 25.33925 },
					{ "time": 0.6333333, "value": 26.11962 },
					{ "time": 0.7333333, "value": 7.45295 },
					{ "time": 0.8666667, "value": -21.19194 },
					{ "time": 1, "value": -26.55841 }
				],
				"translate": [
					{ "x": -1.3240166, "y": 1.706955 },
					{ "time": 0.3666667, "x": -0.06347275, "y": 2.426996 },
					{ "time": 1, "x": -1.3240166, "y": 1.706955 }
				]
			},
			"neck": {
				"rotate": [
					{ "value": 3.6024175 },
					{ "time": 0.13333334, "value": 17.496334 },
					{ "time": 0.23333333, "value": 6.109962 },
					{ "time": 0.3666667, "value": 3.456826 },
					{ "time": 0.5, "value": 5.17656 },
					{ "time": 0.6333333, "value": 18.364304 },
					{ "time": 0.7333333, "value": 6.094681 },
					{ "time": 0.8666667, "value": 2.285569 },
					{ "time": 1, "value": 3.6024175 }
				]
			},
			"pelvis": {
				"rotate": [
					{ "value": -1.33654 }
				],
				"translate": [
					{ "x": 0.391983, "y": -0.7839966 }
				]
			},
			"right-arm": {
				"rotate": [
					{
						"value": -4.029892,
						"curve": [ 0.16925287, -3.906482, 0.5095785, 19.66483 ]
					},
					{
						"time": 0.6333333,
						"value": 19.78824,
						"curve": [ 0.7460727, 19.75366, 0.9220306, -3.906481 ]
					},
					{ "time": 1, "value": -4.029892 }
				]
			},
			"right-foot": {
				"rotate": [
					{ "value": -5.253906 },
					{ "time": 0.23333333, "value": -17.769096 },
					{ "time": 0.3666667, "value": -20.09899 },
					{ "time": 0.5, "value": -19.737137 },
					{ "time": 0.7333333, "value": -11.687042 },
					{ "time": 0.8, "value": 4.465133 },
					{ "time": 0.8666667, "value": 0.4606628 },
					{ "time": 1, "value": -5.253906 }
				]
			},
			"right-hand": {
				"rotate": [
					{ "value": 8.98986 },
					{ "time": 0.6333333, "value": 0.5146103 },
					{ "time": 1, "value": 8.98986 }
				]
			},
			"right-lower-leg": {
				"rotate": [
					{
						"value": -3.392915,
						"curve": [ 0.0421456, -4.011959, 0.09885058, -42.80542 ]
					},
					{
						"time": 0.13333334,
						"value": -43.21811,
						"curve": [ 0.17476194, -43.21811, 0.20390476, -26.0926 ]
					},
					{ "time": 0.23333333, "value": -25.980667 },
					{ "time": 0.5, "value": -19.53301 },
					{ "time": 0.6333333, "value": -64.8023 },
					{
						"time": 0.7333333,
						"value": -89.54278,
						"curve": [ 0.8819923, -73.99887, 1, -3.392914 ]
					},
					{ "time": 1, "value": -3.392914 }
				],
				"translate": [
					{ "time": 0.5 },
					{ "time": 0.6333333, "x": 2.189648, "y": 0.2131157 },
					{ "time": 1 }
				]
			},
			"right-shoulder": {
				"rotate": [
					{
						"value": 5.290283,
						"curve": [ 0.16743295, 5.290283, 0.475, 6.6521 ]
					},
					{ "time": 0.6333333, "value": 6.6521 },
					{ "time": 1, "value": 5.290283 }
				]
			},
			"right-upper-leg": {
				"rotate": [
					{ "value": 42.45098 },
					{
						"time": 0.13333334,
						"value": 49.86462,
						"curve": [ 0.17476194, 49.86462, 0.20390476, 22.69049 ]
					},
					{ "time": 0.23333333, "value": 22.51288 },
					{ "time": 0.5, "value": -16.936226 },
					{ "time": 0.6333333, "value": 1.8974 },
					{
						"time": 0.7333333,
						"value": 34.86858,
						"curve": [ 0.7950191, 37.70707, 0.8666667, 58.68722 ]
					},
					{
						"time": 0.8666667,
						"value": 58.68722,
						"curve": [ 0.9333333, 58.35072, 1, 42.45098 ]
					},
					{ "time": 1, "value": 42.45098 }
				],
				"translate": [
					{ "x": 6.239994 },
					{ "time": 0.23333333, "x": 2.140015, "y": 2.400015 },
					{ "time": 0.5, "x": 2.440014, "y": 4.80003 },
					{ "time": 1, "x": 6.239994 }
				]
			},
			"spear1": {
				"rotate": [
					{ "value": 1.8496704 },
					{ "time": 0.2, "value": -5.389892 },
					{ "time": 0.5, "value": 2.950447 },
					{ "time": 0.7333333, "value": -3.672623 },
					{ "time": 1, "value": 1.8496704 }
				]
			},
			"spear2": {
				"rotate": [
					{ "value": 1.8496705 },
					{ "time": 0.2, "value": -5.389892 },
					{ "time": 0.5, "value": 2.950447 },
					{ "time": 0.7333333, "value": -3.672623 },
					{ "time": 1, "value": 1.8496704 }
				]
			},
			"spear3": {
				"rotate": [
					{ "value": 3.642997 },
					{ "time": 0.2, "value": -3.596566 },
					{ "time": 0.5, "value": 4.743774 },
					{ "time": 0.7333333, "value": -1.879296 },
					{ "time": 1, "value": 3.642997 }
				]
			},
			"torso": {
				"rotate": [
					{ "value": -10.283966 },
					{
						"time": 0.13333334,
						"value": -15.38633,
						"curve": [ 0.260728, -15.357297, 0.3244253, -9.783066 ]
					},
					{
						"time": 0.3666667,
						"value": -9.783066,
						"curve": [ 0.521456, -10.803614, 0.5452107, -15.720798 ]
					},
					{
						"time": 0.6333333,
						"value": -15.751724,
						"curve": [ 0.6883142, -15.661755, 0.8190613, -7.069671 ]
					},
					{
						"time": 0.8666667,
						"value": -7.069671,
						"curve": [ 0.894636, -7.069671, 0.975479, -10.250657 ]
					},
					{ "time": 1, "value": -10.283966 }
				]
			}
		},
		"attachments": {
			"default": {
				"right-hand-item": {
					"dagger": {
						"deform": [
							{
								"offset": 26,
								"vertices": [ 2.3475494, 0.1446953 ],
								"curve": [ 0.125, 0, 0.375, 1 ]
							},
							{
								"time": 0.5,
								"offset": 8,
								"vertices": [ -1.194153, 4.315315, 0.07279014, 6.413513, 1.6604805, 6.188827, 1.7523284, 3.595554 ],
								"curve": [ 0.625, 0, 0.875, 1 ]
							},
							{
								"time": 1,
								"offset": 26,
								"vertices": [ 2.3475494, 0.1446953 ]
							}
						]
					}
				}
			},
			"goblin": {
				"head": {
					"head": {
						"deform": [
							{
								"curve": [ 0.1265715, 0, 0.15, 1 ]
							},
							{
								"time": 0.2,
								"vertices": [ -10.978266, -6.689621, -4.680153, -2.46175, 0, 0, 0, 0, 0, 0, 0, 0, 0, 0, 0, 0, -1.0853424, 0.08391952, -1.0853424, 0.08391952, -1.0853424, 0.08391952, 0, 0, -2.2232475, 2.664654, -4.832952, 2.7008476, -5.70553, -0.519413, -3.159622, -1.615017, 0, 0, 0, 0, 0, 0, 0, 0, 0, 0, 0, 0, -6.647415, 0.8161202, -11.82286, -1.349552, 0, 0, 0, 0, 0, 0, 0, 0, 0, 0, -1.0853424, 0.08391952 ],
								"curve": [ 0.24166666, 0, 0.325, 1 ]
							},
							{
								"time": 0.3666667,
								"vertices": [ 10.692759, 4.059494, 3.6637306, 1.854267, 0, 0, 0, 0, 0, 0, 0, 0, 0, 0, 0, 0, 1.473053, 0.09017944, 1.473053, 0.09017944, 1.473053, 0.09017944, 0, 0, 2.6965275, -0.22738266, 3.771355, 0.1141777, 3.689304, 1.5535202, 2.495949, 1.6550102, 0, 0, 0, 0, 0, 0, 0, 0, 0, 0, 0, 0, 4.458805, -3.911301, 9.195936, -1.668541, 0, 0, 0, 0, 0, 0, 0, 0, 0, 0, 1.473053, 0.09017944 ],
								"curve": [ 0.5738094, 0, 0.6166667, 1 ]
							},
							{
								"time": 0.7,
								"vertices": [ -10.978266, -6.689621, -4.680153, -2.46175, 0, 0, 0, 0, 0, 0, 0, 0, 0, 0, 0, 0, -1.1755066, -0.17183304, -1.1755066, -0.17182922, -1.1755066, -0.17183304, 0, 0, -2.2232475, 2.664654, -4.832952, 2.7008476, -5.70553, -0.519413, -3.159622, -1.615017, 0, 0, 0, 0, 0, 0, 0, 0, 0, 0, 0, 0, -6.647415, 0.8161202, -11.82286, -1.349552, 0, 0, 0, 0, 0, 0, 0, 0, 0, 0, -1.1755066, -0.17183304 ],
								"curve": [ 0.7416667, 0, 0.825, 1 ]
							},
							{
								"time": 0.8666667,
								"vertices": [ 10.692759, 4.059494, 3.6637306, 1.854267, 0, 0, 0, 0, 0, 0, 0, 0, 0, 0, 0, 0, 0.3868713, 0.08446121, 0.3868713, 0.08446121, 0.3868713, 0.08446121, 0, 0, 2.6965275, -0.22738266, 3.771355, 0.1141777, 3.689304, 1.5535202, 2.495949, 1.6550102, 0, 0, 0, 0, 0, 0, 0, 0, 0, 0, 0, 0, 4.458805, -3.911301, 9.195936, -1.668541, 0, 0, 0, 0, 0, 0, 0, 0, 0, 0, 0.3868713, 0.08446121 ],
								"curve": [ 0.9, 0, 0.9666666, 1 ]
							},
							{ "time": 1 }
						]
					}
				},
				"left-foot": {
					"left-foot": {
						"deform": [
							{
								"offset": 8,
								"vertices": [ 3.692982, 2.3757284, -7.169693, 18.797327, -12.781616, 14.777802, -12.75776, 6.50514, -3.134758, 1.9890633, -0.4440155, 0.3662949, 0, 0, -3.800854, 2.984741 ]
							},
							{ "time": 0.13333334 },
							{
								"time": 0.23333333,
								"offset": 8,
								"vertices": [ -3.960728, -2.345944, -5.804458, -12.476292, -2.2312965, -12.990377, 2.029419, -9.103604, 0, 0, 0, 0, 0, 0, -1.352543, -5.288303 ]
							},
							{
								"time": 0.3666667,
								"offset": 8,
								"vertices": [ 0.6650467, 0.33548355, 0.3390236, 2.690144, -0.4817085, 2.545244, -1.135929, 1.385624, 0, 0, 0, 0, 0, 0, -0.1190796, 0.7927311 ]
							},
							{ "time": 0.5, "curve": "stepped" },
							{ "time": 0.6333333 },
							{
								"time": 0.7333333,
								"offset": 8,
								"vertices": [ -2.977375, 9.40254, -6.916611, 19.927944, -10.552872, 18.41085, -12.371613, 12.384733, -4.726068, 6.307989, 0, 0, -1.4890213, 4.889442, -7.06773, 10.701015 ]
							},
							{
								"time": 0.8333333,
								"offset": 6,
								"vertices": [ 1.0531883, 1.563619, -2.527229, 7.997402, -5.52031, 17.14137, -8.93317, 15.796352, -10.737476, 10.220558, -4.23801, 5.369924, 0, 0, 0, 0, -5.831478, 8.555317 ]
							},
							{
								"time": 1,
								"offset": 8,
								"vertices": [ 3.692982, 2.3757284, -7.169693, 18.797327, -12.781616, 14.777802, -12.75776, 6.50514, -3.134758, 1.9890633, -0.4440155, 0.3662949, 0, 0, -3.800854, 2.984741 ]
							}
						]
					}
				},
				"pelvis": {
					"pelvis": {
						"deform": [
							{},
							{
								"time": 0.13333334,
								"offset": 6,
								"vertices": [ -0.6898994, -4.132835 ]
							},
							{
								"time": 0.3333333,
								"offset": 6,
								"vertices": [ -1.049452, -3.104769 ]
							},
							{
								"time": 0.7,
								"offset": 6,
								"vertices": [ -1.4245033, -6.306167 ]
							},
							{
								"time": 0.8666667,
								"offset": 6,
								"vertices": [ -1.135418, -1.7903595 ]
							},
							{ "time": 1 }
						]
					}
				},
				"right-foot": {
					"right-foot": {
						"deform": [
							{},
							{
								"time": 0.13333334,
								"offset": 2,
								"vertices": [ -2.812588, 2.6311474, -2.352383, 3.89441, -1.999214, 4.863905, -0.9327316, 5.579821, -0.4888611, 5.098545, -0.3481255, 3.429125, -0.17445755, 1.3689885, 0, 0, 0, 0, 0, 0, 0, 0, 0, 0, 0, 0, -1.313053, 1.9137168, -1.3298645, 3.6570334 ]
							},
							{
								"time": 0.23333333,
								"offset": 2,
								"vertices": [ -6.39088, 6.412456, -7.74575, 8.271916, -7.024711, 11.358942, -4.034706, 13.934544, -2.50399, 12.629625, -1.4612465, 7.589151, -0.17445755, 1.368988, 0, 0, 0, 0, 0, 0, 0, 0, 0, 0, 0, 0, -3.847656, 2.612158, -4.539558, 7.923575 ]
							},
							{
								"time": 0.3,
								"offset": 2,
								"vertices": [ -8.271847, 6.688217, -9.297642, 10.137975, -8.622314, 14.713396, -4.586296, 18.819393, -2.203041, 17.10709, -0.0779457, 9.904604, 2.5445194, 1.0164223, 0, 0, 0, 0, 0, 0, 0, 0, 0, 0, 0, 0, -2.946247, 2.3800774, -4.593986, 10.01888 ]
							},
							{
								"time": 0.3666667,
								"offset": 2,
								"vertices": [ -10.476837, 9.441755, -13.368828, 12.40983, -14.325687, 16.943924, -9.24463, 23.556744, -5.517116, 21.513777, -1.19582, 11.531925, 2.5445194, 1.0164223, 0, 0, 0, 0, 0, 0, 0, 0, 0, 0, 0, 0, -4.148477, 2.293892, -6.634187, 11.371273 ]
							},
							{
								"time": 0.5,
								"offset": 2,
								"vertices": [ -5.424736, 4.368543, -10.590044, 7.044682, -11.642513, 11.558454, -6.196651, 20.128056, -1.454975, 18.05411, 4.8662, 6.416786, 2.8146286, 0.2760124, 0, 0, 0, 0, 0, 0, 0, 0, 0, 0, 0, 0, 0, 0, -2.964123, 4.948295 ]
							},
							{ "time": 0.6333333 },
							{
								"time": 0.7333333,
								"offset": 4,
								"vertices": [ 1.314621, -6.84099, -0.8790512, -12.544792, -5.9851, -14.083678, -7.158924, -11.631937, -5.679201, -4.835446, 0, 0, 0, 0, 0, 0, 0, 0, 0, 0, 0, 0, 0, 0, 0, 0, -2.061638, -6.938441 ]
							},
							{
								"time": 0.8,
								"offset": 4,
								"vertices": [ 0.6573105, -3.420495, -0.4395256, -6.272396, -2.99255, -7.041838, -3.579464, -5.815969, -2.8395996, -2.417723, 0, 0, 0, 0, 0, 0, 0, 0, 0, 0, 2.796879, -1.2802086, 0, 0, 0, 0, -1.030819, -3.4692204 ]
							},
							{ "time": 0.8666667 }
						]
					}
				},
				"right-hand": {
					"right-hand": {
						"deform": [
							{
								"offset": 4,
								"vertices": [ -1.484169, 0.3473625, 0, 0, 1.3115234, 0.0808525, 1.6029587, 0.09881592, 0.136734, 0.15470505, 0, 0, 0, 0, -0.7286224, -0.0449028 ]
							},
							{ "time": 0.5 },
							{
								"time": 1,
								"offset": 4,
								"vertices": [ -1.484169, 0.3473625, 0, 0, 1.3115234, 0.0808525, 1.6029587, 0.09881592, 0.136734, 0.15470505, 0, 0, 0, 0, -0.7286224, -0.0449028 ]
							}
						]
					}
				},
				"right-lower-leg": {
					"right-lower-leg": {
						"deform": [
							{},
							{
								"time": 0.6,
								"offset": 6,
								"vertices": [ 1.8039627, -1.565525 ]
							},
							{ "time": 1 }
						]
					}
				},
				"right-upper-leg": {
					"right-upper-leg": {
						"deform": [
							{
								"vertices": [ -6.038566, -1.4632492, 0, 0, 0, 0, 0, 0, 0, 0, 0, 0, 0, 0, -0.3468475, -1.931015, -1.8604736, -5.052658, -2.501404, -3.09985 ]
							},
							{ "time": 0.3333333 },
							{
								"time": 0.8666667,
								"offset": 14,
								"vertices": [ 0.13424683, -2.353775, -1.333176, -5.995727, -1.3586197, -4.433235 ]
							},
							{
								"time": 1,
								"vertices": [ -6.038566, -1.4632492, 0, 0, 0, 0, 0, 0, 0, 0, 0, 0, 0, 0, -0.3468475, -1.931015, -1.8604736, -5.052658, -2.501404, -3.09985 ]
							}
						]
					}
				},
				"torso": {
					"torso": {
						"deform": [
							{
								"offset": 2,
								"vertices": [ 0.2482071, 2.866728, 0.2482071, 2.866728, 0.2482071, 2.866728, 0.2482071, 2.866728, 0.2482071, 2.866728, 0.2482071, 2.866728, -1.241314, 2.626516, -2.474922, 0.7118282, -0.2636261, -0.530798, 0.2482071, 2.866728, 0.2482071, 2.866728, 0, 0, 0, 0, 0, 0, 0, 0, 1.344612, 0.2521458, 0.2482071, 2.866728, 0.8250732, 1.617981, 0.2482071, 2.866728, 0, 0, -1.8643112, -0.4325962, 0.2482071, 2.866728 ]
							},
							{
								"time": 0.13333334,
								"offset": 2,
								"vertices": [ 0.3558884, 4.10914, 0.3558884, 4.10914, 0.3558884, 4.10914, 0.3558884, 4.10914, 0.3558884, 4.10914, 0.3558884, 4.10914, 1.669078, 3.5118656, -0.6235542, 2.4797916, 1.1045017, 3.4968395, -1.0900917, 6.084291, 0.3558884, 4.10914, 0, 0, 0, 0, 0, 0, 0, 0, 3.0129066, 0.1569252, 0.3558884, 4.10914, -1.113983, 3.7954025, 0.3558884, 4.10914, 0, 0, -2.961673, 0.5556335, -2.207405, 4.405872 ]
							},
							{
								"time": 0.3,
								"offset": 2,
								"vertices": [ 0.2883987, 3.329483, 0.2883987, 3.329483, 0.2883987, 3.329483, 0.2883987, 3.329483, 0.2883987, 3.329483, 0.2883987, 3.329483, 6.326009, 0.19387054, 7.843155, 1.948372, 7.085871, 3.6411934, 4.52343, 4.469608, 0.2883987, 3.329483, 0, 0, 0, 0, 0, 0, 0, 0, 4.364156, -1.8387623, 0.2883987, 3.329483, 4.292501, 3.60194, 0.2883987, 3.329483, 0, 0, 3.7260056, -0.19337845, 0.2883987, 3.329483 ]
							},
							{
								"time": 0.5,
								"offset": 2,
								"vertices": [ 0.3133011, 3.6165924, 0.3133011, 3.6165924, 0.3133011, 3.6165924, 0.3133011, 3.6165924, 0.3133011, 3.6165924, 0.3133011, 3.6165924, 2.572727, 2.744568, 2.8883076, 3.0479736, 3.4844246, 3.0465546, 1.8003464, 4.609001, 0.3133011, 3.6165924, 0, 0, 0, 0, 0, 0, 0, 0, 3.537815, -0.8220348, 0.3133011, 3.6165924, 1.8002167, 3.6324596, 0.3133011, 3.6165924, 0, 0, 0.627182, 0.33563805, -1.2246742, 3.794632 ]
							},
							{
								"time": 0.6333333,
								"offset": 2,
								"vertices": [ 0.443985, 5.124996, 0.443985, 5.124996, 0.443985, 5.124996, 0.443985, 5.124996, 0.443985, 5.124996, 0.443985, 5.124996, 1.194009, 3.6079826, -0.5354576, 3.4956474, 1.1925983, 4.512695, -1.001995, 7.100147, 0.443985, 5.124996, 0, 0, 0, 0, 0, 0, 0, 0, 3.101003, 1.172781, 0.443985, 5.124996, -1.0258865, 4.811258, 0.443985, 5.124996, 0, 0, -2.873576, 1.5714893, -2.1193085, 5.421728 ]
							},
							{
								"time": 0.8666667,
								"offset": 2,
								"vertices": [ 0.3038483, 3.50647, 0.3038483, 3.50647, 0.3038483, 3.50647, 0.3038483, 3.50647, 0.3038483, 3.50647, 0.3038483, 3.50647, 0.925869, 2.243847, 0.6887398, 1.2994537, 3.554329, 3.0060425, 2.714935, 5.899624, 0.3038483, 3.50647, 0, 0, 0, 0, 0, 0, 0, 0, 1.967749, 0.4054756, 0.3038483, 3.50647, 2.610399, 2.354502, 0.3038483, 3.50647, 0, 0, 0.22708607, -0.1285095, -0.6282577, 3.614372 ]
							},
							{
								"time": 1,
								"offset": 2,
								"vertices": [ 0.3280182, 3.7882595, 0.3280182, 3.7882595, 0.3280182, 3.7882595, 0.3280182, 3.7882595, 0.3280182, 3.7882595, 0.3280182, 3.7882595, -1.161503, 3.548048, -2.395111, 1.63336, -0.183815, 0.3907337, 0.3280182, 3.7882595, 0.3280182, 3.7882595, 0, 0, 0, 0, 0, 0, 0, 0, 1.4244232, 1.1736774, 0.3280182, 3.7882595, 0.9048843, 2.5395126, 0.3280182, 3.7882595, 0, 0, -1.7845, 0.4889355, 0.3280182, 3.7882595 ]
							}
						]
					}
				},
				"undie-straps": {
					"undie-straps": {
						"deform": [
							{
								"offset": 2,
								"vertices": [ -1.776966, 0.5475998, -0.9614506, -1.0379333, -0.3914814, -0.24071503, -1.776966, 0.5475998 ]
							},
							{
								"time": 0.13333334,
								"offset": 2,
								"vertices": [ -2.256836, -1.0317707, -1.4971943, -4.238615, -0.7446995, -2.849067, -1.9007244, 0.544775 ]
							},
							{
								"time": 0.3333333,
								"offset": 2,
								"vertices": [ -2.379741, -0.05431652, -0.4943333, 0.19436646, -0.9086132, 1.1651926, -1.60956, 2.707987, 0.9618606, 0.8061523 ]
							},
							{
								"time": 0.7,
								"offset": 2,
								"vertices": [ -0.9171452, -2.765671, -0.6221485, -3.6348934, -0.8494091, -2.267721, -2.560768, 0.5297088 ]
							},
							{
								"time": 0.8666667,
								"offset": 2,
								"vertices": [ -2.560768, 0.5297088, -1.5806465, 0.3203125, -1.3847008, 0.3247604, -2.560768, 0.5297088 ]
							},
							{
								"time": 1,
								"offset": 2,
								"vertices": [ -1.776966, 0.5475998, -0.801281, 0.534134, -0.801281, 0.534134, -1.776966, 0.5475998 ]
							}
						]
					}
				},
				"undies": {
					"undies": {
						"deform": [
							{
								"vertices": [ 0.4309883, 0.7220001, 10.602953, -0.11699676, 2.295986, 0, 2.295986, 0, 2.295986, 0, 0.5879879, 0.24399567, -2.4001846, -0.6533508, -2.278204, -0.7753372, 2.295986, 0, 0.587986, -0.487999, 4.986976, -0.11699676, 6.507968, -0.23399353 ]
							},
							{
								"time": 0.13333334,
								"vertices": [ 0.7265901, 0.4331999, 7.204169, -0.16380167, 1.3775916, 0, 1.3775916, 0, 1.3775916, 0, 1.2527905, 0.04640031, -0.9986172, -2.95085, -1.3754253, -3.0740414, 1.3775914, 0, 0.3527918, -0.292799, 2.9921856, -0.07019806, 3.904781, -0.1403961 ]
							},
							{
								"time": 0.3333333,
								"vertices": [ 1.1699924, 0, 2.105994, -0.2340088, 0, 0, 0, 0, 0, 0, 2.2499924, -0.24999237, -0.4344025, 0.6055145, -1.559395, 0.4805145 ]
							},
							{
								"time": 0.5333333,
								"vertices": [ 1.1699924, 0, -0.2340021, -0.935997, -2.924991, 0.3509979, 0, 0, 0, 0, 0.4999962, -0.24999237, -0.6407852, -2.079147, -0.6407852, -2.079147 ]
							},
							{
								"time": 0.7,
								"vertices": [ 1.8627052, -0.11514282, 4.663266, -0.09099793, -1.7642808, 0.21171284, 0, 0, -0.5683284, 0.3283272, -1.1383333, -1.1511085, -2.1999626, -3.47068, -1.2971878, -3.47068, 0, 0, 0, 0, 1.5878525, -0.04642725, 2.6594176, 0.167145 ]
							},
							{
								"time": 0.8333333,
								"vertices": [ 2.416876, -0.20725727, 8.581082, 0.5850014, -0.835712, 0.10028553, 0, 0, -1.0229912, 0.5909881, -2.4489975, -1.8720014, -1.6249962, 0, 0, 0, 0, 0, 0, 0, 2.858135, -0.08356905, 4.786952, 0.3008609 ]
							},
							{
								"time": 0.8666667,
								"vertices": [ 2.019698, -0.021405697, 8.985456, 0.4446018, -0.20937204, 0.0802288, 0.4591976, 0, -0.3591952, 0.4727907, -1.8415995, -1.4488018, -0.7915325, 1.2642074, 0.5328598, 1.23981, 0.4591978, 0, 0.11759758, -0.09759998, 3.2839036, -0.09025454, 5.131155, 0.19388986 ]
							},
							{
								"time": 1,
								"vertices": [ 0.4309883, 0.7220001, 10.602953, -0.11699676, 2.295986, 0, 2.295986, 0, 2.295986, 0, 0.5879879, 0.24399567, -2.4001846, -0.6533508, -2.278204, -0.7753372, 2.295986, 0, 0.587986, -0.487999, 4.986976, -0.11699676, 6.507968, -0.23399353 ]
							}
						]
					}
				}
			}
		}
	}
}
}